file_swirl/__init__.py
file_swirl/cli.py
file_swirl/constants.py
file_swirl/file_sorter.py
file_swirl/file_structs.py
file_swirl/file_update.py
file_swirl/get_metadata.py
file_swirl/gps.py
file_swirl/logger.py
file_swirl/meta_extract.py
file_swirl/utils.py
file_swirl-0.0.11.dist-info/licenses/LICENSE
tests/__init__.py
tests/test_regex.py
file_swirl-0.0.11.dist-info/METADATA
file_swirl-0.0.11.dist-info/WHEEL
file_swirl-0.0.11.dist-info/entry_points.txt
file_swirl-0.0.11.dist-info/top_level.txt
file_swirl-0.0.11.dist-info/RECORD
