Metadata-Version: 2.4
Name: file-swirl
Version: 0.0.11
Summary: A fast, flexible file sorter and organizer
Author: Nishant Ghanate
License: MIT License
Project-URL: Homepage, https://github.com/NishantGhanate/FileSwirl
Project-URL: Documentation, https://github.com/NishantGhanate/FileSwirl#readme
Project-URL: Source, https://github.com/NishantGhanate/FileSwirl
Project-URL: Tracker, https://github.com/NishantGhanate/FileSwirl/issues
Requires-Python: >=3.8
License-File: LICENSE
Requires-Dist: setuptools
Requires-Dist: ExifRead==3.0.0
Requires-Dist: pytest==8.4.1
Requires-Dist: colorlog==6.9.0
Dynamic: license-file
